[
  { "id": 1, "pertanyaan": "Untuk memotong buah kita menggunakan...", "jawaban_benar": ["pisau", "cutter", "silet", "cutter"] },
  { "id": 2, "pertanyaan": "Ibu menggoreng tempe di atas...", "jawaban_benar": ["wajan", "penggorengan", "teflon"] },
  { "id": 3, "pertanyaan": "Kita memakai payung agar tidak...", "jawaban_benar": ["kehujanan", "basah", "kepanasan"] },
  { "id": 4, "pertanyaan": "Siswa menulis di buku menggunakan...", "jawaban_benar": ["pulpen", "pensil", "spidol", "bolpoin"] },
  { "id": 5, "pertanyaan": "Lampu lalu lintas warna merah artinya...", "jawaban_benar": ["berhenti", "stop"] },
  { "id": 6, "pertanyaan": "Kita menghirup udara menggunakan...", "jawaban_benar": ["hidung", "paru-paru"] },
  { "id": 7, "pertanyaan": "Alat untuk menunjuk arah mata angin adalah...", "jawaban_benar": ["kompas"] },
  { "id": 8, "pertanyaan": "Supaya bersih, kita mencuci baju dengan...", "jawaban_benar": ["sabun", "deterjen", "detergen"] },
  { "id": 9, "pertanyaan": "Benda yang digunakan untuk menyisir rambut adalah...", "jawaban_benar": ["sisir"] },
  { "id": 10, "pertanyaan": "Sebelum makan, sebaiknya kita membaca...", "jawaban_benar": ["doa", "do'a"] },
  { "id": 11, "pertanyaan": "Alat untuk melihat benda angkasa adalah...", "jawaban_benar": ["teleskop", "teropong"] },
  { "id": 12, "pertanyaan": "Ikan bernapas di dalam air menggunakan...", "jawaban_benar": ["insang"] },
  { "id": 13, "pertanyaan": "Presiden pertama Indonesia adalah...", "jawaban_benar": ["soekarno", "ir soekarno"] },
  { "id": 14, "pertanyaan": "Alat untuk mengukur suhu tubuh adalah...", "jawaban_benar": ["termometer"] },
  { "id": 15, "pertanyaan": "Sepatu dipakai di bagian...", "jawaban_benar": ["kaki"] },
  { "id": 16, "pertanyaan": "Kita mendengarkan musik menggunakan telinga atau...", "jawaban_benar": ["earphone", "headset", "headphone", "speaker"] },
  { "id": 17, "pertanyaan": "Minuman yang berasal dari perasan jeruk disebut...", "jawaban_benar": ["jus jeruk", "es jeruk", "sari jeruk"] },
  { "id": 18, "pertanyaan": "Alat untuk merapikan rumput adalah...", "jawaban_benar": ["sabit", "gunting rumput", "mesin rumput"] },
  { "id": 19, "pertanyaan": "Tempat untuk menyimpan uang di bank disebut...", "jawaban_benar": ["tabungan", "rekening"] },
  { "id": 20, "pertanyaan": "Benda yang digunakan untuk menghapus tulisan pensil adalah...", "jawaban_benar": ["penghapus", "stipo", "tipe x"] },
  { "id": 21, "pertanyaan": "Ibu kota Indonesia saat ini adalah...", "jawaban_benar": ["jakarta", "ikn", "nusantara"] },
  { "id": 22, "pertanyaan": "Sapi menghasilkan minuman sehat yaitu...", "jawaban_benar": ["susu"] },
  { "id": 23, "pertanyaan": "Rasa cabai adalah...", "jawaban_benar": ["pedas"] },
  { "id": 24, "pertanyaan": "Awan yang mendung menandakan akan turun...", "jawaban_benar": ["hujan"] },
  { "id": 25, "pertanyaan": "Alat transportasi udara yang sangat besar adalah...", "jawaban_benar": ["pesawat", "pesawat terbang"] },
  { "id": 26, "pertanyaan": "Gula memiliki rasa yang...", "jawaban_benar": ["manis"] },
  { "id": 27, "pertanyaan": "Garam memiliki rasa yang...", "jawaban_benar": ["asin"] },
  { "id": 28, "pertanyaan": "Matahari terbit dari sebelah...", "jawaban_benar": ["timur"] },
  { "id": 29, "pertanyaan": "Matahari terbenam di sebelah...", "jawaban_benar": ["barat"] },
  { "id": 30, "pertanyaan": "Benda yang bisa memantulkan bayangan kita adalah...", "jawaban_benar": ["cermin", "kaca"] },
  { "id": 31, "pertanyaan": "Kamera digunakan untuk mengambil...", "jawaban_benar": ["foto", "gambar", "video"] },
  { "id": 32, "pertanyaan": "Kita tidur di atas...", "jawaban_benar": ["kasur", "tempat tidur", "ranjang"] },
  { "id": 33, "pertanyaan": "Benda yang digunakan untuk menyapu lantai adalah...", "jawaban_benar": ["sapu"] },
  { "id": 34, "pertanyaan": "Alat untuk melindungi kepala saat naik motor adalah...", "jawaban_benar": ["helm"] },
  { "id": 35, "pertanyaan": "Mengepel lantai menggunakan kain...", "jawaban_benar": ["pel"] },
  { "id": 36, "pertanyaan": "Ayah membaca berita di...", "jawaban_benar": ["koran", "surat kabar", "internet", "hp"] },
  { "id": 37, "pertanyaan": "Sandal jepit dipakai di...", "jawaban_benar": ["kaki"] },
  { "id": 38, "pertanyaan": "Burung terbang menggunakan...", "jawaban_benar": ["sayap"] },
  { "id": 39, "pertanyaan": "Ular berjalan dengan cara...", "jawaban_benar": ["melata", "merayap"] },
  { "id": 40, "pertanyaan": "Lampu senter memerlukan tenaga dari...", "jawaban_benar": ["baterai", "batre"] },
  { "id": 41, "pertanyaan": "Kita memakai jam tangan di...", "jawaban_benar": ["lengan", "pergelangan tangan", "tangan"] },
  { "id": 42, "pertanyaan": "Alat musik yang dipetik adalah...", "jawaban_benar": ["gitar", "ukulele", "kecapi"] },
  { "id": 43, "pertanyaan": "Alat musik yang ditiup adalah...", "jawaban_benar": ["seruling", "trompet", "pianika", "saksofon"] },
  { "id": 44, "pertanyaan": "Mobil memiliki roda berjumlah...", "jawaban_benar": ["empat", "4"] },
  { "id": 45, "pertanyaan": "Motor memiliki roda berjumlah...", "jawaban_benar": ["dua", "2"] },
  { "id": 46, "pertanyaan": "Warna bendera Indonesia adalah merah dan...", "jawaban_benar": ["putih"] },
  { "id": 47, "pertanyaan": "Pelangi muncul setelah terjadi...", "jawaban_benar": ["hujan"] },
  { "id": 48, "pertanyaan": "Buah yang kulitnya berduri adalah...", "jawaban_benar": ["durian", "salak"] },
  { "id": 49, "pertanyaan": "Alat untuk mengeringkan rambut disebut...", "jawaban_benar": ["hair dryer"] },
  { "id": 50, "pertanyaan": "Kita mengunyah makanan menggunakan...", "jawaban_benar": ["gigi"] },
  { "id": 51, "pertanyaan": "Rumah bagi lebah disebut...", "jawaban_benar": ["sarang"] },
  { "id": 52, "pertanyaan": "Alat untuk memaku kayu adalah...", "jawaban_benar": ["palu", "martil"] },
  { "id": 53, "pertanyaan": "Dokter memeriksa pasien di...", "jawaban_benar": ["rumah sakit", "puskesmas", "klinik"] },
  { "id": 54, "pertanyaan": "Benda yang digunakan untuk mengunci pintu adalah...", "jawaban_benar": ["kunci"] },
  { "id": 55, "pertanyaan": "Kita melihat menggunakan...", "jawaban_benar": ["mata"] },
  { "id": 56, "pertanyaan": "Hewan yang suaranya 'petok-petok' adalah...", "jawaban_benar": ["ayam"] },
  { "id": 57, "pertanyaan": "Hewan yang suaranya 'meong' adalah...", "jawaban_benar": ["kucing"] },
  { "id": 58, "pertanyaan": "Tempat mendarat pesawat adalah...", "jawaban_benar": ["bandara", "bandar udara"] },
  { "id": 59, "pertanyaan": "Tempat berhentinya kereta api disebut...", "jawaban_benar": ["stasiun"] },
  { "id": 60, "pertanyaan": "Tempat berhentinya bus disebut...", "jawaban_benar": ["terminal"] },
  { "id": 61, "pertanyaan": "Alat untuk menimbang berat badan adalah...", "jawaban_benar": ["timbangan"] },
  { "id": 62, "pertanyaan": "Kita mandi agar tubuh menjadi...", "jawaban_benar": ["bersih", "wangi", "segar"] },
  { "id": 63, "pertanyaan": "Cuci tangan sebelum makan agar terhindar dari...", "jawaban_benar": ["kuman", "bakteri", "penyakit"] },
  { "id": 64, "pertanyaan": "Benda yang digunakan untuk minum adalah...", "jawaban_benar": ["gelas", "cangkir", "botol"] },
  { "id": 65, "pertanyaan": "Benda yang digunakan untuk makan nasi adalah...", "jawaban_benar": ["piring", "sendok"] },
  { "id": 66, "pertanyaan": "Madu dihasilkan oleh...", "jawaban_benar": ["lebah"] },
  { "id": 67, "pertanyaan": "Alat untuk mengambil nasi adalah...", "jawaban_benar": ["centong"] },
  { "id": 68, "pertanyaan": "Setelah olahraga tubuh mengeluarkan...", "jawaban_benar": ["keringat"] },
  { "id": 69, "pertanyaan": "Haus adalah tanda tubuh kekurangan...", "jawaban_benar": ["air", "cairan", "minum"] },
  { "id": 70, "pertanyaan": "Lapar adalah tanda perut sedang...", "jawaban_benar": ["kosong", "minta makan"] },
  { "id": 71, "pertanyaan": "Alat untuk menyiram bunga adalah...", "jawaban_benar": ["teko penyiram", "selang"] },
  { "id": 72, "pertanyaan": "Benda yang diletakkan di bawah kepala saat tidur adalah...", "jawaban_benar": ["bantal"] },
  { "id": 73, "pertanyaan": "Benda yang dipeluk saat tidur adalah...", "jawaban_benar": ["guling", "boneka"] },
  { "id": 74, "pertanyaan": "Kita mencuci rambut menggunakan...", "jawaban_benar": ["shampo", "sampo"] },
  { "id": 75, "pertanyaan": "Gosok gigi menggunakan odol dan...", "jawaban_benar": ["sikat gigi"] },
  { "id": 76, "pertanyaan": "Alat untuk memanaskan air adalah...", "jawaban_benar": ["teko", "panci", "dispenser"] },
  { "id": 77, "pertanyaan": "Agar tidak kedinginan saat tidur kita memakai...", "jawaban_benar": ["selimut"] },
  { "id": 78, "pertanyaan": "Kompor digunakan untuk...", "jawaban_benar": ["memasak"] },
  { "id": 79, "pertanyaan": "Hutan adalah paru-paru...", "jawaban_benar": ["dunia", "bumi"] },
  { "id": 80, "pertanyaan": "Tempat membuang sampah adalah...", "jawaban_benar": ["tempat sampah", "tong sampah"] },
  { "id": 81, "pertanyaan": "Alat untuk menjahit baju adalah...", "jawaban_benar": ["jarum", "benang", "mesin jahit"] },
  { "id": 82, "pertanyaan": "Benda yang bisa terbang karena ditiup angin adalah...", "jawaban_benar": ["layangan", "layang-layang"] },
  { "id": 83, "pertanyaan": "Alat untuk mengukur panjang adalah...", "jawaban_benar": ["penggaris", "meteran"] },
  { "id": 84, "pertanyaan": "Olahraga yang menendang bola disebut...", "jawaban_benar": ["sepak bola", "futsal"] },
  { "id": 85, "pertanyaan": "Olahraga yang menggunakan raket adalah...", "jawaban_benar": ["bulutangkis", "tenis", "badminton"] },
  { "id": 86, "pertanyaan": "Alat untuk menggali tanah adalah...", "jawaban_benar": ["cangkul", "sekop"] },
  { "id": 87, "pertanyaan": "Sandal atau sepatu diletakkan di...", "jawaban_benar": ["rak sepatu"] },
  { "id": 88, "pertanyaan": "Orang yang mengemudikan pesawat disebut...", "jawaban_benar": ["pilot"] },
  { "id": 89, "pertanyaan": "Orang yang mengemudikan kereta api disebut...", "jawaban_benar": ["masinis"] },
  { "id": 90, "pertanyaan": "Orang yang mengemudikan kapal laut disebut...", "jawaban_benar": ["nakhoda", "nahkoda"] },
  { "id": 91, "pertanyaan": "Awan berwarna putih, kalau mendung berwarna...", "jawaban_benar": ["abu-abu", "gelap", "hitam"] },
  { "id": 92, "pertanyaan": "Daun pada umumnya berwarna...", "jawaban_benar": ["hijau"] },
  { "id": 93, "pertanyaan": "Darah manusia berwarna...", "jawaban_benar": ["merah"] },
  { "id": 94, "pertanyaan": "Air laut rasanya...", "jawaban_benar": ["asin"] },
  { "id": 95, "pertanyaan": "Gunung meletus mengeluarkan...", "jawaban_benar": ["lava", "magma", "abu vulkanik"] },
  { "id": 96, "pertanyaan": "Alat untuk berteduh dari hujan selain payung adalah...", "jawaban_benar": ["jas hujan"] },
  { "id": 97, "pertanyaan": "Hewan peliharaan yang bisa bicara adalah burung...", "jawaban_benar": ["beo", "kakak tua"] },
  { "id": 98, "pertanyaan": "Bulan terlihat pada malam...", "jawaban_benar": ["hari"] },
  { "id": 99, "pertanyaan": "Bintang bersinar pada...", "jawaban_benar": ["malam hari"] },
  { "id": 100, "pertanyaan": "Tangan kita berjumlah...", "jawaban_benar": ["dua", "2"] },
  { "id": 101, "pertanyaan": "Pelajar belajar di...", "jawaban_benar": ["sekolah", "kelas", "rumah"] },
  { "id": 102, "pertanyaan": "Guru mengajar di depan...", "jawaban_benar": ["kelas", "papan tulis", "murid"] },
  { "id": 103, "pertanyaan": "Alat untuk menghaluskan bumbu dapur adalah...", "jawaban_benar": ["blender", "ulekan", "cobek"] },
  { "id": 104, "pertanyaan": "Kita menyimpan es batu di dalam...", "jawaban_benar": ["kulkas", "freezer", "termos es"] },
  { "id": 105, "pertanyaan": "Nasi berasal dari...", "jawaban_benar": ["beras", "padi"] },
  { "id": 106, "pertanyaan": "Alat untuk menyalakan televisi adalah...", "jawaban_benar": ["remote", "remot"] },
  { "id": 107, "pertanyaan": "Kita memakai sabuk atau ikat pinggang di...", "jawaban_benar": ["pinggang", "celana"] },
  { "id": 108, "pertanyaan": "Topi dipakai untuk melindungi...", "jawaban_benar": ["kepala"] },
  { "id": 109, "pertanyaan": "Kacamata membantu kita untuk...", "jawaban_benar": ["melihat", "membaca"] },
  { "id": 110, "pertanyaan": "Hewan yang memiliki leher sangat panjang adalah...", "jawaban_benar": ["jerapah"] },
  { "id": 111, "pertanyaan": "Hewan yang memiliki belalai adalah...", "jawaban_benar": ["gajah"] },
  { "id": 112, "pertanyaan": "Hewan yang jalannya sangat lambat adalah...", "jawaban_benar": ["kura-kura", "siput", "keong"] },
  { "id": 113, "pertanyaan": "Buah pisang biasanya berwarna...", "jawaban_benar": ["kuning", "hijau"] },
  { "id": 114, "pertanyaan": "Alat untuk mendinginkan ruangan adalah...", "jawaban_benar": ["ac", "kipas angin"] },
  { "id": 115, "pertanyaan": "Kita menelepon orang lain menggunakan...", "jawaban_benar": ["hp", "ponsel", "telepon"] },
  { "id": 116, "pertanyaan": "Tempat untuk menonton film di layar besar adalah...", "jawaban_benar": ["bioskop", "cinema"] },
  { "id": 117, "pertanyaan": "Pedagang berjualan di...", "jawaban_benar": ["pasar", "toko", "warung", "mall"] },
  { "id": 118, "pertanyaan": "Alat untuk menyuci piring adalah...", "jawaban_benar": ["spons", "sabun cuci piring"] },
  { "id": 119, "pertanyaan": "Hujan salju biasanya terjadi di musim...", "jawaban_benar": ["dingin", "salju", "winter"] },
  { "id": 120, "pertanyaan": "Bunga mawar biasanya memiliki batang yang...", "jawaban_benar": ["berduri", "duri"] },
  { "id": 121, "pertanyaan": "Arah jarum jam bergerak ke arah...", "jawaban_benar": ["kanan"] },
  { "id": 122, "pertanyaan": "Alat untuk menancapkan paku adalah...", "jawaban_benar": ["palu", "martil"] },
  { "id": 123, "pertanyaan": "Tinta pulpen biasanya berwarna hitam atau...", "jawaban_benar": ["biru", "merah"] },
  { "id": 124, "pertanyaan": "Jika ingin pintar kita harus rajin...", "jawaban_benar": ["belajar", "membaca"] },
  { "id": 125, "pertanyaan": "Kelinci sangat suka makan...", "jawaban_benar": ["wortel", "sayur"] },
  { "id": 126, "pertanyaan": "Alat untuk menjepit jemuran adalah...", "jawaban_benar": ["jepitan", "jepit jemuran"] },
  { "id": 127, "pertanyaan": "Benda yang digunakan untuk menambal ban adalah...", "jawaban_benar": ["karet", "lem", "ban dalam"] },
  { "id": 128, "pertanyaan": "Kita bisa melihat bintang menggunakan alat...", "jawaban_benar": ["teleskop", "teropong"] },
  { "id": 129, "pertanyaan": "Petani menanam padi di...", "jawaban_benar": ["sawah"] },
  { "id": 130, "pertanyaan": "Nelayan mencari ikan di...", "jawaban_benar": ["laut", "sungai", "danau"] },
  { "id": 131, "pertanyaan": "Kita memakai kaos kaki sebelum memakai...", "jawaban_benar": ["sepatu"] },
  { "id": 132, "pertanyaan": "Alat untuk merekatkan kertas adalah...", "jawaban_benar": ["lem", "selotip", "isolasi"] },
  { "id": 133, "pertanyaan": "Bentuk bumi adalah...", "jawaban_benar": ["bulat", "bola"] },
  { "id": 134, "pertanyaan": "Tempat untuk memarkir mobil disebut...", "jawaban_benar": ["parkiran", "garasi"] },
  { "id": 135, "pertanyaan": "Untuk masuk ke rumah kita melewati...", "jawaban_benar": ["pintu"] },
  { "id": 136, "pertanyaan": "Untuk melihat pemandangan ke luar rumah lewat...", "jawaban_benar": ["jendela"] },
  { "id": 137, "pertanyaan": "Cahaya senter berasal dari lampu dan...", "jawaban_benar": ["baterai", "batre"] },
  { "id": 138, "pertanyaan": "Hewan yang menghasilkan telur adalah...", "jawaban_benar": ["ayam", "bebek", "burung", "ikan"] },
  { "id": 139, "pertanyaan": "Minyak goreng terbuat dari kelapa...", "jawaban_benar": ["sawit"] },
  { "id": 140, "pertanyaan": "Benda yang bisa menarik besi adalah...", "jawaban_benar": ["magnet"] },
  { "id": 141, "pertanyaan": "Laba-laba membuat...", "jawaban_benar": ["jaring"] },
  { "id": 142, "pertanyaan": "Alat untuk menyiram tanaman adalah...", "jawaban_benar": ["selang", "teko penyiram"] },
  { "id": 143, "pertanyaan": "Orang yang memimpin sebuah desa adalah...", "jawaban_benar": ["lurah", "kepala desa"] },
  { "id": 144, "pertanyaan": "Ibu kota Jawa Tengah adalah...", "jawaban_benar": ["semarang"] },
  { "id": 145, "pertanyaan": "Ibu kota Jawa Barat adalah...", "jawaban_benar": ["bandung"] },
  { "id": 146, "pertanyaan": "Ibu kota Jawa Timur adalah...", "jawaban_benar": ["surabaya"] },
  { "id": 147, "pertanyaan": "Kita mendengar petir setelah melihat...", "jawaban_benar": ["kilat", "petir", "cahaya"] },
  { "id": 148, "pertanyaan": "Kita mengeringkan badan setelah mandi menggunakan...", "jawaban_benar": ["handuk"] },
  { "id": 149, "pertanyaan": "Gigi yang kotor bisa menyebabkan...", "jawaban_benar": ["sakit gigi", "berlubang", "kuman"] },
  { "id": 150, "pertanyaan": "Alat untuk menanak nasi secara otomatis adalah...", "jawaban_benar": ["magic com", "rice cooker"] },
  { "id": 151, "pertanyaan": "Mandi menggunakan air dan...", "jawaban_benar": ["sabun"] },
  { "id": 152, "pertanyaan": "Kereta api berjalan di atas...", "jawaban_benar": ["rel"] },
  { "id": 153, "pertanyaan": "Kera sangat suka makan buah...", "jawaban_benar": ["pisang"] },
  { "id": 154, "pertanyaan": "Hewan yang melompat dan punya kantong adalah...", "jawaban_benar": ["kanguru"] },
  { "id": 155, "pertanyaan": "Kaktus biasanya tumbuh di...", "jawaban_benar": ["padang pasir", "gurun"] },
  { "id": 156, "pertanyaan": "Kapal selam bergerak di dalam...", "jawaban_benar": ["air", "laut"] },
  { "id": 157, "pertanyaan": "Supaya tidak digigit nyamuk kita memakai...", "jawaban_benar": ["obat nyamuk", "lotion nyamuk"] },
  { "id": 158, "pertanyaan": "Sapi memakan...", "jawaban_benar": ["rumput"] },
  { "id": 159, "pertanyaan": "Alat untuk menutup luka kecil adalah...", "jawaban_benar": ["plester", "hansaplast"] },
  { "id": 160, "pertanyaan": "Ban kendaraan terbuat dari...", "jawaban_benar": ["karet"] },
  { "id": 161, "pertanyaan": "Benda yang digunakan untuk mengasah pisau adalah...", "jawaban_benar": ["batu asah", "gerinda"] },
  { "id": 162, "pertanyaan": "Kita mencium bau menggunakan...", "jawaban_benar": ["hidung"] },
  { "id": 163, "pertanyaan": "Kita merasakan rasa makanan menggunakan...", "jawaban_benar": ["lidah"] },
  { "id": 164, "pertanyaan": "Alat untuk mematikan atau menyalakan lampu adalah...", "jawaban_benar": ["saklar"] },
  { "id": 165, "pertanyaan": "Supaya tidak kepanasan di siang hari kita memakai...", "jawaban_benar": ["topi", "payung"] },
  { "id": 166, "pertanyaan": "Buku yang berisi peta dunia disebut...", "jawaban_benar": ["atlas"] },
  { "id": 167, "pertanyaan": "Alat untuk memotong kertas secara lurus adalah...", "jawaban_benar": ["penggaris", "cutter"] },
  { "id": 168, "pertanyaan": "Tempat untuk membuang air kecil atau besar disebut...", "jawaban_benar": ["toilet", "wc", "kamar mandi"] },
  { "id": 169, "pertanyaan": "Pakaian yang basah harus di...", "jawaban_benar": ["jemur", "keringkan"] },
  { "id": 170, "pertanyaan": "Ayah mencukur jenggot menggunakan...", "jawaban_benar": ["silet", "alat cukur"] },
  { "id": 171, "pertanyaan": "Kita memakai syal di bagian...", "jawaban_benar": ["leher"] },
  { "id": 172, "pertanyaan": "Lampu yang ada di jalan raya disebut lampu...", "jawaban_benar": ["jalan", "penerangan"] },
  { "id": 173, "pertanyaan": "Katak bergerak dengan cara...", "jawaban_benar": ["melompat"] },
  { "id": 174, "pertanyaan": "Air yang membeku disebut...", "jawaban_benar": ["es"] },
  { "id": 175, "pertanyaan": "Air yang mendidih mengeluarkan...", "jawaban_benar": ["uap"] },
  { "id": 176, "pertanyaan": "Supaya badan sehat kita harus rajin...", "jawaban_benar": ["olahraga"] },
  { "id": 177, "pertanyaan": "Baju yang kusut harus di...", "jawaban_benar": ["setrika"] },
  { "id": 178, "pertanyaan": "Alat untuk meratakan baju yang kusut adalah...", "jawaban_benar": ["setrika"] },
  { "id": 179, "pertanyaan": "Tempat untuk menyimpan pakaian adalah...", "jawaban_benar": ["lemari"] },
  { "id": 180, "pertanyaan": "Alat untuk membatalkan tulisan yang salah adalah...", "jawaban_benar": ["penghapus", "tipe x"] },
  { "id": 181, "pertanyaan": "Komputer dioperasikan menggunakan...", "jawaban_benar": ["keyboard", "mouse"] },
  { "id": 182, "pertanyaan": "Benda yang bisa terbang karena diisi gas adalah...", "jawaban_benar": ["balon"] },
  { "id": 183, "pertanyaan": "Kita menulis di papan tulis menggunakan kapur atau...", "jawaban_benar": ["spidol"] },
  { "id": 184, "pertanyaan": "Warna langit pada siang hari yang cerah adalah...", "jawaban_benar": ["biru"] },
  { "id": 185, "pertanyaan": "Gajah memiliki hidung panjang yang disebut...", "jawaban_benar": ["belalai"] },
  { "id": 186, "pertanyaan": "Harimau memiliki gigi yang tajam yang disebut...", "jawaban_benar": ["taring"] },
  { "id": 187, "pertanyaan": "Benda yang berbunyi saat ada tamu datang adalah...", "jawaban_benar": ["bel"] },
  { "id": 188, "pertanyaan": "Kita mengisi bensin di...", "jawaban_benar": ["spbu", "pom bensin"] },
  { "id": 189, "pertanyaan": "Alat untuk menaruh piring yang basah adalah...", "jawaban_benar": ["rak piring"] },
  { "id": 190, "pertanyaan": "Pelampung digunakan agar tidak...", "jawaban_benar": ["tenggelam"] },
  { "id": 191, "pertanyaan": "Kita mencuci tangan menggunakan sabun dan...", "jawaban_benar": ["air"] },
  { "id": 192, "pertanyaan": "Orang yang bertugas memadamkan api adalah...", "jawaban_benar": ["pemadam kebakaran"] },
  { "id": 193, "pertanyaan": "Kita membeli obat di...", "jawaban_benar": ["apotek"] },
  { "id": 194, "pertanyaan": "Hewan yang jalannya miring adalah...", "jawaban_benar": ["kepiting"] },
  { "id": 195, "pertanyaan": "Kacang hijau bisa tumbuh menjadi...", "jawaban_benar": ["tauge", "toge", "kecambah"] },
  { "id": 196, "pertanyaan": "Alat untuk mengupas kulit buah adalah...", "jawaban_benar": ["peeler", "pisau"] },
  { "id": 197, "pertanyaan": "Untuk masuk ke akun sosial media kita butuh kata...", "jawaban_benar": ["sandi", "password"] },
  { "id": 198, "pertanyaan": "Jika haus kita harus...", "jawaban_benar": ["minum"] },
  { "id": 199, "pertanyaan": "Jika mengantuk kita harus...", "jawaban_benar": ["tidur"] },
  { "id": 200, "pertanyaan": "Ikan hiu hidup di...", "jawaban_benar": ["laut", "air"] },
  { "id": 201, "pertanyaan": "Alat untuk menghitung secara cepat adalah...", "jawaban_benar": ["kalkulator"] },
  { "id": 202, "pertanyaan": "Ibu menyimpan sayuran agar tetap segar di...", "jawaban_benar": ["kulkas", "lemari es"] },
  { "id": 203, "pertanyaan": "Kita menaruh sampah plastik di...", "jawaban_benar": ["tempat sampah", "tong sampah"] },
  { "id": 204, "pertanyaan": "Bagian pohon yang berada di dalam tanah adalah...", "jawaban_benar": ["akar"] },
  { "id": 205, "pertanyaan": "Alat untuk menjahit kain adalah jarum dan...", "jawaban_benar": ["benang"] },
  { "id": 206, "pertanyaan": "Benda yang digunakan untuk mengelap keringat adalah...", "jawaban_benar": ["tisu", "sapu tangan", "handuk"] },
  { "id": 207, "pertanyaan": "Kita memakai sabun saat mandi agar kuman...", "jawaban_benar": ["mati", "hilang", "bersih"] },
  { "id": 208, "pertanyaan": "Alat untuk memindahkan kursor di komputer adalah...", "jawaban_benar": ["mouse"] },
  { "id": 209, "pertanyaan": "Hewan yang pandai melompat di pohon adalah...", "jawaban_benar": ["monyet", "kera", "tupai"] },
  { "id": 110, "pertanyaan": "Seseorang yang ahli memasak di restoran disebut...", "jawaban_benar": ["koki", "chef"] },
  { "id": 211, "pertanyaan": "Alat untuk menyedot debu di karpet adalah...", "jawaban_benar": ["vacuum cleaner", "penyedot debu"] },
  { "id": 212, "pertanyaan": "Kita memerlukan kunci untuk membuka...", "jawaban_benar": ["pintu", "gembok", "laci"] },
  { "id": 213, "pertanyaan": "Benda yang mengeluarkan suara saat jam weker berbunyi adalah...", "jawaban_benar": ["alarm"] },
  { "id": 214, "pertanyaan": "Kita bisa melihat waktu di dinding menggunakan...", "jawaban_benar": ["jam dinding"] },
  { "id": 215, "pertanyaan": "Alat untuk merebus mie instan adalah...", "jawaban_benar": ["panci"] },
  { "id": 216, "pertanyaan": "Satu minggu terdiri dari tujuh...", "jawaban_benar": ["hari"] },
  { "id": 217, "pertanyaan": "Setelah hari Senin adalah hari...", "jawaban_benar": ["selasa"] },
  { "id": 218, "pertanyaan": "Sebelum hari Minggu adalah hari...", "jawaban_benar": ["sabtu"] },
  { "id": 219, "pertanyaan": "Ibu memotong bawang menggunakan pisau dan alasnya yaitu...", "jawaban_benar": ["talenan"] },
  { "id": 220, "pertanyaan": "Benda yang ditiup wasit saat pertandingan bola adalah...", "jawaban_benar": ["peluit"] },
  { "id": 221, "pertanyaan": "Alat untuk menyisir rambut agar rapi adalah...", "jawaban_benar": ["sisir"] },
  { "id": 222, "pertanyaan": "Kita menulis di papan tulis putih menggunakan...", "jawaban_benar": ["spidol"] },
  { "id": 223, "pertanyaan": "Alat untuk melubangi kertas adalah...", "jawaban_benar": ["perforator", "pembolong kertas"] },
  { "id": 224, "pertanyaan": "Benda yang digunakan untuk menambal ban bocor adalah...", "jawaban_benar": ["lem", "karet"] },
  { "id": 225, "pertanyaan": "Seseorang yang bertugas menjaga keamanan desa adalah...", "jawaban_benar": ["hansip", "satpam"] },
  { "id": 226, "pertanyaan": "Lampu lalu lintas warna hijau artinya boleh...", "jawaban_benar": ["jalan", "maju"] },
  { "id": 227, "pertanyaan": "Alat untuk memarut kelapa atau keju disebut...", "jawaban_benar": ["parutan"] },
  { "id": 228, "pertanyaan": "Tempat untuk memajang foto di dinding adalah...", "jawaban_benar": ["bingkai", "pigura"] },
  { "id": 229, "pertanyaan": "Kita memakai sarung tangan agar tangan tidak...", "jawaban_benar": ["dingin", "kotor", "panas"] },
  { "id": 230, "pertanyaan": "Alat untuk mengukur berat buah di pasar adalah...", "jawaban_benar": ["timbangan"] },
  { "id": 231, "pertanyaan": "Minuman kopi rasanya cenderung...", "jawaban_benar": ["pahit"] },
  { "id": 232, "pertanyaan": "Obat biasanya memiliki rasa yang...", "jawaban_benar": ["pahit"] },
  { "id": 233, "pertanyaan": "Alat untuk menghirup minuman dari gelas adalah...", "jawaban_benar": ["sedotan"] },
  { "id": 234, "pertanyaan": "Kita menaruh piring dan gelas kotor di...", "jawaban_benar": ["wastafel", "tempat cuci piring"] },
  { "id": 235, "pertanyaan": "Lantai yang kotor harus segera di...", "jawaban_benar": ["sapu", "pel"] },
  { "id": 236, "pertanyaan": "Orang yang suka melawak disebut...", "jawaban_benar": ["pelawak", "komedian"] },
  { "id": 237, "pertanyaan": "Alat untuk merekam suara adalah...", "jawaban_benar": ["perekam", "recorder", "hp"] },
  { "id": 238, "pertanyaan": "Kita memakai jas hujan saat berkendara di waktu...", "jawaban_benar": ["hujan"] },
  { "id": 239, "pertanyaan": "Benda yang berputar di atas atap rumah untuk sirkulasi udara adalah...", "jawaban_benar": ["ventilasi", "turbin ventilator"] },
  { "id": 240, "pertanyaan": "Kita bisa melihat peta digital menggunakan aplikasi...", "jawaban_benar": ["maps", "google maps"] },
  { "id": 241, "pertanyaan": "Hewan yang jalannya melompat dan makan rumput adalah...", "jawaban_benar": ["kelinci", "belalang"] },
  { "id": 242, "pertanyaan": "Kayu berasal dari batang...", "jawaban_benar": ["pohon"] },
  { "id": 243, "pertanyaan": "Alat untuk menyatukan dua kertas tanpa lem adalah...", "jawaban_benar": ["stepler", "hekter"] },
  { "id": 244, "pertanyaan": "Kita meletakkan buku-buku agar rapi di...", "jawaban_benar": ["rak buku", "perpustakaan"] },
  { "id": 245, "pertanyaan": "Pakaian yang sudah dicuci harus dijemur di bawah sinar...", "jawaban_benar": ["matahari"] },
  { "id": 246, "pertanyaan": "Jika ingin memotong kuku menggunakan...", "jawaban_benar": ["gunting kuku"] },
  { "id": 247, "pertanyaan": "Alat untuk menyaring teh agar ampasnya hilang adalah...", "jawaban_benar": ["saringan"] },
  { "id": 248, "pertanyaan": "Tempat mendaratnya helikopter disebut...", "jawaban_benar": ["helipad"] },
  { "id": 249, "pertanyaan": "Burung bernapas menggunakan paru-paru dan pundi-pundi...", "jawaban_benar": ["udara"] },
  { "id": 250, "pertanyaan": "Hewan yang menyimpan cadangan air di punuknya adalah...", "jawaban_benar": ["unta"] },
  { "id": 251, "pertanyaan": "Kertas terbuat dari serat...", "jawaban_benar": ["kayu", "pohon"] },
  { "id": 252, "pertanyaan": "Alat untuk mengecas baterai hp adalah...", "jawaban_benar": ["charger", "casan"] },
  { "id": 253, "pertanyaan": "Seseorang yang bertugas mengantar surat disebut...", "jawaban_benar": ["tukang pos", "kurir"] },
  { "id": 254, "pertanyaan": "Alat untuk mencongkel paku adalah...", "jawaban_benar": ["linggis", "palu"] },
  { "id": 255, "pertanyaan": "Kita mencuci muka menggunakan air dan...", "jawaban_benar": ["sabun muka", "facial wash"] },
  { "id": 256, "pertanyaan": "Benda yang digunakan untuk meneduhkan halaman rumah adalah...", "jawaban_benar": ["kanopi", "tenda"] },
  { "id": 257, "pertanyaan": "Alat untuk melihat kuman yang sangat kecil adalah...", "jawaban_benar": ["mikroskop"] },
  { "id": 258, "pertanyaan": "Kita menaruh bumbu dapur seperti garam di dalam...", "jawaban_benar": ["toples", "wadah"] },
  { "id": 259, "pertanyaan": "Padi yang sudah dikupas kulitnya disebut...", "jawaban_benar": ["beras"] },
  { "id": 260, "pertanyaan": "Beras yang sudah dimasak disebut...", "jawaban_benar": ["nasi"] },
  { "id": 261, "pertanyaan": "Alat untuk mengeringkan tangan di toilet umum adalah...", "jawaban_benar": ["hand dryer", "tisu"] },
  { "id": 262, "pertanyaan": "Petugas yang mengatur lalu lintas adalah...", "jawaban_benar": ["polisi", "polantas"] },
  { "id": 263, "pertanyaan": "Kita menyeberang jalan melalui...", "jawaban_benar": ["zebra cross", "jembatan penyeberangan"] },
  { "id": 264, "pertanyaan": "Alat untuk mengetik di komputer disebut...", "jawaban_benar": ["keyboard"] },
  { "id": 265, "pertanyaan": "Buah semangka dalamnya berwarna merah atau...", "jawaban_benar": ["kuning"] },
  { "id": 266, "pertanyaan": "Ibu menggoreng kerupuk menggunakan minyak...", "jawaban_benar": ["goreng"] },
  { "id": 267, "pertanyaan": "Alat untuk mengupas bawang adalah...", "jawaban_benar": ["pisau"] },
  { "id": 268, "pertanyaan": "Tempat untuk menaruh uang kertas dan kartu disebut...", "jawaban_benar": ["dompet"] },
  { "id": 269, "pertanyaan": "Kita mematikan tv jika sudah tidak...", "jawaban_benar": ["ditonton", "dilihat"] },
  { "id": 270, "pertanyaan": "Benda yang digunakan untuk menyumbat telinga dari bising adalah...", "jawaban_benar": ["earplug"] },
  { "id": 271, "pertanyaan": "Alat untuk menarik benda yang tenggelam di sumur adalah...", "jawaban_benar": ["katrol", "tali timba"] },
  { "id": 272, "pertanyaan": "Kita menaruh pakaian kotor di dalam...", "jawaban_benar": ["keranjang"] },
  { "id": 273, "pertanyaan": "Seseorang yang memimpin pertandingan bola disebut...", "jawaban_benar": ["wasit"] },
  { "id": 274, "pertanyaan": "Alat untuk meniup api pada kompor kayu adalah...", "jawaban_benar": ["semprong", "pipa besi"] },
  { "id": 275, "pertanyaan": "Kita memakai parfum agar badan menjadi...", "jawaban_benar": ["wangi", "harum"] },
  { "id": 276, "pertanyaan": "Halaman rumah dibersihkan menggunakan sapu...", "jawaban_benar": ["lidi"] },
  { "id": 277, "pertanyaan": "Lantai dalam rumah dibersihkan menggunakan sapu...", "jawaban_benar": ["ijuk", "lantai"] },
  { "id": 278, "pertanyaan": "Benda yang mengeluarkan cahaya saat mati lampu adalah...", "jawaban_benar": ["lilin", "senter", "lampu darurat"] },
  { "id": 279, "pertanyaan": "Alat untuk menghaluskan kayu adalah...", "jawaban_benar": ["amplas", "ketam"] },
  { "id": 280, "pertanyaan": "Seseorang yang bertugas memandu wisata disebut...", "jawaban_benar": ["pemandu wisata", "tour guide"] },
  { "id": 281, "pertanyaan": "Kita menaruh bunga di dalam...", "jawaban_benar": ["vas", "pot"] },
  { "id": 282, "pertanyaan": "Alat untuk melubangi tembok adalah...", "jawaban_benar": ["bor"] },
  { "id": 283, "pertanyaan": "Kita memotong kertas menggunakan pisau atau...", "jawaban_benar": ["gunting"] },
  { "id": 284, "pertanyaan": "Benda yang ditarik kuda pada delman adalah...", "jawaban_benar": ["kereta", "gerobak"] },
  { "id": 285, "pertanyaan": "Alat untuk mengukur tekanan darah adalah...", "jawaban_benar": ["tensimeter"] },
  { "id": 286, "pertanyaan": "Kita memakai helm saat naik motor untuk melindungi...", "jawaban_benar": ["kepala"] },
  { "id": 287, "pertanyaan": "Benda yang digunakan untuk menambal gigi adalah...", "jawaban_benar": ["semen gigi", "komposit"] },
  { "id": 288, "pertanyaan": "Kita melihat berita di televisi atau...", "jawaban_benar": ["hp", "ponsel", "internet"] },
  { "id": 289, "pertanyaan": "Alat untuk menggulung benang layangan adalah...", "jawaban_benar": ["kaleng", "bladu"] },
  { "id": 290, "pertanyaan": "Kita minum susu agar tulang menjadi...", "jawaban_benar": ["kuat", "sehat"] },
  { "id": 291, "pertanyaan": "Orang yang bekerja di sawah disebut...", "jawaban_benar": ["petani"] },
  { "id": 292, "pertanyaan": "Orang yang bekerja mencari ikan disebut...", "jawaban_benar": ["nelayan"] },
  { "id": 293, "pertanyaan": "Alat untuk memutar baut adalah...", "jawaban_benar": ["obeng"] },
  { "id": 294, "pertanyaan": "Alat untuk memutar mur adalah...", "jawaban_benar": ["kunci pas", "kunci inggris"] },
  { "id": 295, "pertanyaan": "Kita memakai kaos tangan saat memasak agar tidak...", "jawaban_benar": ["panas", "terbakar"] },
  { "id": 296, "pertanyaan": "Benda yang digunakan untuk membersihkan telinga adalah...", "jawaban_benar": ["cotton bud"] },
  { "id": 297, "pertanyaan": "Kita menanam pohon agar udara menjadi...", "jawaban_benar": ["segar", "sejuk", "bersih"] },
  { "id": 298, "pertanyaan": "Matahari memberikan energi panas dan...", "jawaban_benar": ["cahaya"] },
  { "id": 299, "pertanyaan": "Alat untuk menyatukan dua besi dengan panas disebut...", "jawaban_benar": ["las", "mesin las"] },
  { "id": 300, "pertanyaan": "Kita menggunakan jaket saat cuaca...", "jawaban_benar": ["dingin"] }
  
]